[{"Name":"Samtse","Names":["Samchi","Samtse"],"Code":"14","CountryAlpha2":"BT","longitude":"","latitude":"","MinLongitude":89.0766335,"MinLatitude":26.9078347,"MaxLongitude":89.090538,"MaxLatitude":26.9162536,"Latitude":26.9131041,"Longitude":89.08360189999999},{"Name":"Punakha","Names":["Punakha"],"Code":"23","CountryAlpha2":"BT","longitude":"","latitude":"","MinLongitude":89.8721123,"MinLatitude":27.5877193,"MaxLongitude":89.88554479999999,"MaxLatitude":27.5961249,"Latitude":27.5920869,"Longitude":89.87974589999999},{"Name":"Sarpang","Names":["Gaylegphug","Geylegphug","Sarbhang","Sarpang"],"Code":"31","CountryAlpha2":"BT","longitude":"","latitude":"","MinLongitude":89.734461,"MinLatitude":26.7076319,"MaxLongitude":90.96380099999999,"MaxLatitude":27.209321,"Latitude":26.9373041,"Longitude":90.4879916},{"Name":"Lhuentse","Names":["Lhuentse","Lhun Tshi","Lhuntshi","Lhuntsi"],"Code":"44","CountryAlpha2":"BT","longitude":"","latitude":"","MinLongitude":91.1688424,"MinLatitude":27.6492443,"MaxLongitude":91.1892156,"MaxLatitude":27.677438,"Latitude":27.6649208,"Longitude":91.1761004},{"Name":"Ha","Names":["Ha","Haa"],"Code":"13","CountryAlpha2":"BT","longitude":"","latitude":"","MinLongitude":88.89505199999999,"MinLatitude":27.0723781,"MaxLongitude":89.39598099999999,"MaxLatitude":27.6211449,"Latitude":27.2651669,"Longitude":89.1705998},{"Name":"Chhukha","Names":["Chhuka","Chuka","Chukha"],"Code":"12","CountryAlpha2":"BT","longitude":"","latitude":"","MinLongitude":89.5604609,"MinLatitude":27.0483479,"MaxLongitude":89.5806313,"MaxLatitude":27.0611895,"Latitude":27.0522919,"Longitude":89.5756987},{"Name":"Wangdue Phodrang","Names":["Wangdi Phodrang","Wangdiphodrang","Wangdue","Wangdue Phodrang"],"Code":"24","CountryAlpha2":"BT","longitude":"","latitude":"","MinLongitude":89.8926686,"MinLatitude":27.474542,"MaxLongitude":89.9055432,"MaxLatitude":27.4991359,"Latitude":27.4879018,"Longitude":89.8996196},{"Name":"Bumthang","Names":["Bumthang"],"Code":"33","CountryAlpha2":"BT","longitude":"","latitude":"","MinLongitude":90.48443499999999,"MinLatitude":27.320946,"MaxLongitude":91.0160089,"MaxLatitude":28.090851,"Latitude":27.641839,"Longitude":90.6773046},{"Name":"Zhemgang","Names":["Shemgang","Zhemgang"],"Code":"34","CountryAlpha2":"BT","longitude":"","latitude":"","MinLongitude":90.6856155,"MinLatitude":27.1353061,"MaxLongitude":90.69565779999999,"MaxLatitude":27.1492833,"Latitude":27.1439047,"Longitude":90.6903529},{"Name":"Monggar","Names":["Monggar","Mongor"],"Code":"42","CountryAlpha2":"BT","longitude":"","latitude":"","MinLongitude":91.23415949999999,"MinLatitude":27.2708807,"MaxLongitude":91.2454034,"MaxLatitude":27.280493,"Latitude":27.275,"Longitude":91.24},{"Name":"Samdrup Jongkha","Names":["Samdruk Jongkhar","Samdrup","Samdrup Jongkha"],"Code":"45","CountryAlpha2":"BT","longitude":"","latitude":"","MinLongitude":90.995525,"MinLatitude":26.777367,"MaxLongitude":92.1221539,"MaxLatitude":27.2464701,"Latitude":26.928696,"Longitude":91.63721500000001},{"Name":"Trashi Yangtse","Names":["Tashiyangtse"],"Code":"TY","CountryAlpha2":"BT","longitude":"","latitude":"","MinLongitude":91.31767270000002,"MinLatitude":27.383962,"MaxLongitude":91.73789980000001,"MaxLatitude":28.050773,"Latitude":27.583333,"Longitude":91.466667},{"Name":"Paro","Names":["Paro","Rinpung"],"Code":"11","CountryAlpha2":"BT","longitude":"","latitude":"","MinLongitude":89.131271,"MinLatitude":27.1771741,"MaxLongitude":89.563836,"MaxLatitude":27.7510569,"Latitude":27.4285949,"Longitude":89.4166516},{"Name":"Trongsa","Names":["Tongsa","Trongsa"],"Code":"32","CountryAlpha2":"BT","longitude":"","latitude":"","MinLongitude":90.5036116,"MinLatitude":27.4940347,"MaxLongitude":90.51571369999999,"MaxLatitude":27.508043,"Latitude":27.5002269,"Longitude":90.5080634},{"Name":"Trashigang","Names":["Tashigang","Trashigang"],"Code":"41","CountryAlpha2":"BT","longitude":"","latitude":"","MinLongitude":91.378786,"MinLatitude":27.0165199,"MaxLongitude":92.12519789999999,"MaxLatitude":27.482902,"Latitude":27.2566795,"Longitude":91.7538817},{"Name":"Gasa","Names":["Gaza"],"Code":"GA","CountryAlpha2":"BT","longitude":"","latitude":"","MinLongitude":89.43694289999999,"MinLatitude":27.687483,"MaxLongitude":90.617648,"MaxLatitude":28.323778,"Latitude":28.0185886,"Longitude":89.9253233},{"Name":"Thimphu","Names":["Thimbu","Thimphu","Thimpu","Timbhu","Timbu","Timphu"],"Code":"15","CountryAlpha2":"BT","longitude":"","latitude":"","MinLongitude":89.60414879999999,"MinLatitude":27.4251092,"MaxLongitude":89.6726418,"MaxLatitude":27.5336949,"Latitude":27.4727924,"Longitude":89.6392863},{"Name":"Dagana","Names":["Daga","Dagana"],"Code":"22","CountryAlpha2":"BT","longitude":"","latitude":"","MinLongitude":89.648614,"MinLatitude":26.808901,"MaxLongitude":90.08144100000001,"MaxLatitude":27.26369,"Latitude":27.0322861,"Longitude":89.8879304},{"Name":"Pemagatshel","Names":["Pema Gatshel","Pemagatsel"],"Code":"43","CountryAlpha2":"BT","longitude":"","latitude":"","MinLongitude":91.17381700000001,"MinLatitude":26.8459449,"MaxLongitude":91.517646,"MaxLatitude":27.1670959,"Latitude":27.002382,"Longitude":91.3469247},{"Name":"Tsirang","Names":["Chirang","Tsirang"],"Code":"21","CountryAlpha2":"BT","longitude":"","latitude":"","MinLongitude":90.00392509999999,"MinLatitude":26.8187539,"MaxLongitude":90.357412,"MaxLatitude":27.177361,"Latitude":27.032207,"Longitude":90.1869644}]