[{"Name":"Kinshasa","Names":["Kinshasa"],"Code":"KN","CountryAlpha2":"CD","longitude":"","latitude":"","MinLongitude":15.1764986,"MinLatitude":-4.5093664,"MaxLongitude":15.4694102,"MaxLatitude":-4.2934483,"Latitude":-4.325,"Longitude":15.322222},{"Name":"Kasai-Occidental","Names":["Kasai-Occidental"],"Code":"KW","CountryAlpha2":"CD","longitude":"","latitude":"","MinLongitude":19.6801381,"MinLatitude":-7.9022269,"MaxLongitude":23.742881,"MaxLatitude":-2.338351,"Latitude":-5.320547299999999,"Longitude":21.8568586},{"Name":"Maniema","Names":["Maniema"],"Code":"MA","CountryAlpha2":"CD","longitude":"","latitude":"","MinLongitude":24.456906,"MinLatitude":-5.000742499999999,"MaxLongitude":28.8420401,"MaxLatitude":-0.082443,"Latitude":-3.0730929,"Longitude":26.0413889},{"Name":"Nord-Kivu","Names":["Nord-Kivu"],"Code":"NK","CountryAlpha2":"CD","longitude":"","latitude":"","MinLongitude":27.201624,"MinLatitude":-2.0661759,"MaxLongitude":29.984388,"MaxLatitude":0.9623669,"Latitude":-0.7917729,"Longitude":29.0459927},{"Name":"Bas-Congo","Names":["Bas-Zaire"],"Code":"BC","CountryAlpha2":"CD","longitude":"","latitude":"","MinLongitude":12.206631,"MinLatitude":-6.0573001,"MaxLongitude":16.2585949,"MaxLatitude":-4.279237999999999,"Latitude":-5.2365685,"Longitude":13.914399},{"Name":"Équateur","Names":["Équateur"],"Code":"EQ","CountryAlpha2":"CD","longitude":"","latitude":"","MinLongitude":16.5381639,"MinLatitude":-2.529217,"MaxLongitude":24.4267169,"MaxLatitude":5.14574,"Latitude":0.5640035999999999,"Longitude":20.3308814},{"Name":"Katanga","Names":["Shaba"],"Code":"KA","CountryAlpha2":"CD","longitude":"","latitude":"","MinLongitude":21.744753,"MinLatitude":-13.455676,"MaxLongitude":30.5928848,"MaxLatitude":-4.999066,"Latitude":-8.8851145,"Longitude":26.419389},{"Name":"Kasai-Oriental","Names":["Kasai-Oriental"],"Code":"KE","CountryAlpha2":"CD","longitude":"","latitude":"","MinLongitude":21.9100151,"MinLatitude":-7.9387741,"MaxLongitude":26.265937,"MaxLatitude":-1.738482,"Latitude":-2.8437453,"Longitude":23.3823545},{"Name":"Sud-Kivu","Names":["Sud-Kivu"],"Code":"SK","CountryAlpha2":"CD","longitude":"","latitude":"","MinLongitude":26.798393,"MinLatitude":-4.9999781,"MaxLongitude":29.2644927,"MaxLatitude":-1.568222,"Latitude":-3.011658,"Longitude":28.299435},{"Name":"Bandundu","Names":["Bandundu"],"Code":"BN","CountryAlpha2":"CD","longitude":"","latitude":"","MinLongitude":17.3576054,"MinLatitude":-3.3406136,"MaxLongitude":17.4044975,"MaxLatitude":-3.2987836,"Latitude":-3.316667,"Longitude":17.366667},{"Name":"Orientale","Names":["Haut-Zaire","Orientale"],"Code":"OR","CountryAlpha2":"CD","longitude":"","latitude":"","MinLongitude":22.2904529,"MinLatitude":-2.1170779,"MaxLongitude":31.2769461,"MaxLatitude":5.386098,"Latitude":1.6406296,"Longitude":26.419389}]