[{"Name":"Beja","Names":["Beja"],"Code":"02","CountryAlpha2":"PT","longitude":"","latitude":"","MinLongitude":-7.959504799999999,"MinLatitude":37.97009,"MaxLongitude":-7.8177491,"MaxLatitude":38.0746209,"Latitude":38.0153039,"Longitude":-7.8627308},{"Name":"Faro","Names":["Faro"],"Code":"08","CountryAlpha2":"PT","longitude":"","latitude":"","MinLongitude":-8.000400599999999,"MinLatitude":36.9617104,"MaxLongitude":-7.8093544,"MaxLatitude":37.0738998,"Latitude":37.0193548,"Longitude":-7.9304397},{"Name":"Guarda","Names":["Guarda"],"Code":"09","CountryAlpha2":"PT","longitude":"","latitude":"","MinLongitude":-7.2926517,"MinLatitude":40.50446,"MaxLongitude":-7.1980682,"MaxLatitude":40.5738913,"Latitude":40.5383482,"Longitude":-7.266131499999998},{"Name":"Portalegre","Names":["Portalegre"],"Code":"12","CountryAlpha2":"PT","longitude":"","latitude":"","MinLongitude":-7.4664739,"MinLatitude":39.262495,"MaxLongitude":-7.3995175,"MaxLatitude":39.3153866,"Latitude":39.2967086,"Longitude":-7.4284755},{"Name":"Viseu","Names":["Viseu"],"Code":"18","CountryAlpha2":"PT","longitude":"","latitude":"","MinLongitude":-7.9660481,"MinLatitude":40.6072458,"MaxLongitude":-7.8250273,"MaxLatitude":40.7325793,"Latitude":40.6565861,"Longitude":-7.9124712},{"Name":"Castelo Branco","Names":["Castelo Branco"],"Code":"05","CountryAlpha2":"PT","longitude":"","latitude":"","MinLongitude":-7.5591241,"MinLatitude":39.7136873,"MaxLongitude":-7.367089999999999,"MaxLatitude":39.9093461,"Latitude":39.8197117,"Longitude":-7.4964662},{"Name":"Coimbra","Names":["Coimbra"],"Code":"06","CountryAlpha2":"PT","longitude":"","latitude":"","MinLongitude":-8.5096411,"MinLatitude":40.1713722,"MaxLongitude":-8.322907599999999,"MaxLatitude":40.2861477,"Latitude":40.2033145,"Longitude":-8.4102573},{"Name":"Porto","Names":["Porto"],"Code":"13","CountryAlpha2":"PT","longitude":"","latitude":"","MinLongitude":-8.6910927,"MinLatitude":41.1383506,"MaxLongitude":-8.5526134,"MaxLatitude":41.1859353,"Latitude":41.1579438,"Longitude":-8.629105299999999},{"Name":"Madeira","Names":["Madeira"],"Code":"30","CountryAlpha2":"PT","longitude":"","latitude":"","MinLongitude":-17.2659373,"MinLatitude":30.0303451,"MaxLongitude":-15.8566922,"MaxLatitude":33.1281375,"Latitude":32.76070740000001,"Longitude":-16.9594723},{"Name":"Vila Real","Names":["Vila Real"],"Code":"17","CountryAlpha2":"PT","longitude":"","latitude":"","MinLongitude":-7.790294800000001,"MinLatitude":41.2401615,"MaxLongitude":-7.6639146,"MaxLatitude":41.3635472,"Latitude":41.3010351,"Longitude":-7.7422354},{"Name":"Açores","Names":["Açores"],"Code":"20","CountryAlpha2":"PT","longitude":"","latitude":"","MinLongitude":-31.2687948,"MinLatitude":36.9278178,"MaxLongitude":-25.0131855,"MaxLatitude":39.7261497,"Latitude":37.7412488,"Longitude":-25.6755944},{"Name":"Aveiro","Names":["Aveiro"],"Code":"01","CountryAlpha2":"PT","longitude":"","latitude":"","MinLongitude":-8.665443800000002,"MinLatitude":40.6241712,"MaxLongitude":-8.6238121,"MaxLatitude":40.6545896,"Latitude":40.6405055,"Longitude":-8.6537539},{"Name":"Bragança","Names":["Bragança"],"Code":"04","CountryAlpha2":"PT","longitude":"","latitude":"","MinLongitude":-6.7907131,"MinLatitude":41.7861053,"MaxLongitude":-6.7063504,"MaxLatitude":41.8369891,"Latitude":41.8061131,"Longitude":-6.756737999999999},{"Name":"Évora","Names":["Évora"],"Code":"07","CountryAlpha2":"PT","longitude":"","latitude":"","MinLongitude":-7.9785036,"MinLatitude":38.5227211,"MaxLongitude":-7.843514600000001,"MaxLatitude":38.6169193,"Latitude":38.571431,"Longitude":-7.913501999999999},{"Name":"Leiria","Names":["Leiria"],"Code":"10","CountryAlpha2":"PT","longitude":"","latitude":"","MinLongitude":-8.8768517,"MinLatitude":39.70991799999999,"MaxLongitude":-8.7350657,"MaxLatitude":39.798205,"Latitude":39.74953310000001,"Longitude":-8.807682999999999},{"Name":"Lisboa","Names":["Lisboa"],"Code":"11","CountryAlpha2":"PT","longitude":"","latitude":"","MinLongitude":-9.2298356,"MinLatitude":38.6913994,"MaxLongitude":-9.0905718,"MaxLatitude":38.7958538,"Latitude":38.7222524,"Longitude":-9.1393366},{"Name":"Santarém","Names":["Santarém"],"Code":"14","CountryAlpha2":"PT","longitude":"","latitude":"","MinLongitude":-8.7494918,"MinLatitude":39.1687465,"MaxLongitude":-8.626665299999999,"MaxLatitude":39.2869109,"Latitude":39.2366618,"Longitude":-8.686011900000002},{"Name":"Braga","Names":["Braga"],"Code":"03","CountryAlpha2":"PT","longitude":"","latitude":"","MinLongitude":-8.4806633,"MinLatitude":41.510402,"MaxLongitude":-8.3421791,"MaxLatitude":41.5841477,"Latitude":41.5454486,"Longitude":-8.426506999999999},{"Name":"Setúbal","Names":["Setúbal"],"Code":"15","CountryAlpha2":"PT","longitude":"","latitude":"","MinLongitude":-8.9725114,"MinLatitude":38.4840016,"MaxLongitude":-8.7556919,"MaxLatitude":38.5641093,"Latitude":38.5260437,"Longitude":-8.8909328},{"Name":"Viana do Castelo","Names":["Viana do Castelo"],"Code":"16","CountryAlpha2":"PT","longitude":"","latitude":"","MinLongitude":-8.8693403,"MinLatitude":41.6714037,"MaxLongitude":-8.7483575,"MaxLatitude":41.7605686,"Latitude":41.6918275,"Longitude":-8.8344101}]