[{"Name":"Funafuti","Names":["Funafuti"],"Code":"FUN","CountryAlpha2":"TV","longitude":"","latitude":"","MinLongitude":0,"MinLatitude":0,"MaxLongitude":0,"MaxLatitude":0,"Latitude":-8.516667,"Longitude":179.216667},{"Name":"Niutao","Names":["Niutao"],"Code":"NIT","CountryAlpha2":"TV","longitude":"","latitude":"","MinLongitude":177.3293352,"MinLatitude":-6.1153794,"MaxLongitude":177.3547411,"MaxLatitude":-6.101596499999999,"Latitude":-6.106425799999999,"Longitude":177.3438429},{"Name":"Nui","Names":["Nui"],"Code":"NIU","CountryAlpha2":"TV","longitude":"","latitude":"","MinLongitude":177.1461329,"MinLatitude":-7.246044599999999,"MaxLongitude":177.16564,"MaxLatitude":-7.1889099,"Latitude":-7.2426288,"Longitude":177.1485716},{"Name":"Nukufetau","Names":["Nukufetau"],"Code":"NKF","CountryAlpha2":"TV","longitude":"","latitude":"","MinLongitude":0,"MinLatitude":0,"MaxLongitude":0,"MaxLatitude":0,"Latitude":0,"Longitude":178.5},{"Name":"Nukulaelae","Names":["Nukulailai"],"Code":"NKL","CountryAlpha2":"TV","longitude":"","latitude":"","MinLongitude":0,"MinLatitude":0,"MaxLongitude":0,"MaxLatitude":0,"Latitude":-9.381110999999999,"Longitude":179.852222},{"Name":"Nanumea","Names":["Nanumea"],"Code":"NMA","CountryAlpha2":"TV","longitude":"","latitude":"","MinLongitude":176.109885,"MinLatitude":-5.7013769,"MaxLongitude":176.1365461,"MaxLatitude":-5.6620781,"Latitude":-5.681538799999999,"Longitude":176.1281065},{"Name":"Nanumanga","Names":["Nanumaga"],"Code":"NMG","CountryAlpha2":"TV","longitude":"","latitude":"","MinLongitude":176.3118553,"MinLatitude":-6.302335999999999,"MaxLongitude":176.32579,"MaxLatitude":-6.2772891,"Latitude":-6.2910708,"Longitude":176.314856},{"Name":"Vaitupu","Names":["Vaitupu"],"Code":"VAI","CountryAlpha2":"TV","longitude":"","latitude":"","MinLongitude":178.6624575,"MinLatitude":-7.4991106,"MaxLongitude":178.6972833,"MaxLatitude":-7.4577731,"Latitude":-7.476732699999999,"Longitude":178.6747675}]