{"name":{"common":"Mali","official":"Republic of Mali","Native":{"fra":{"common":"Mali","official":"République du Mali"}}},"EuMember":false,"LandLocked":true,"Nationality":"","tld":[".ml"],"Languages":{"fra":"French"},"Translations":{"FIN":{"common":"Mali","official":"Malin tasavalta"},"HRV":{"common":"Mali","official":"Republika Mali"},"ITA":{"common":"Mali","official":"Repubblica del Mali"},"NLD":{"common":"Mali","official":"Republiek Mali"},"RUS":{"common":"Мали","official":"Республика Мали"},"SPA":{"common":"Mali","official":"República de Malí"}},"currency":["XOF"],"Borders":["DZA","BFA","GIN","CIV","MRT","NER","SEN"],"cca2":"ML","cca3":"MLI","CIOC":"MLI","CCN3":"466","callingCode":["223"],"InternationalPrefix":"00","region":"Africa","subregion":"Western Africa","Continent":"Africa","capital":"Bamako","Area":1.240192e+06,"longitude":"4 00 W","latitude":"17 00 N","MinLongitude":-12.55,"MinLatitude":10.15,"MaxLongitude":13,"MaxLatitude":26,"Latitude":17.35776710510254,"Longitude":-3.5273818969726562}